[
    {
        "id": "1",
        "name": "John Doe",
        "date": "2023-10-29",
        "startTime": 9,
        "duration": 5,
        "service": "Flyttstäd"
    }, 
    {
        "id": "2",
        "name": "Jane Doe",
        "date": "2023-10-30",
        "startTime": 9,
        "duration": 2,
        "service": "Fönsterputs"
    },
    {
        "id": "3",
        "name": "Jamal Doe",
        "date": "2023-10-23",
        "startTime": 13,
        "duration": 3,
        "service": "Vardagsstädning"
    }
]